stormer/__init__.py
stormer/constants.py
stormer/redis_utils.py
stormer/requester.py
stormer/utils.py
test/__init__.py
test/tests.py
stormer-0.1.2.dist-info/LICENSE
stormer-0.1.2.dist-info/METADATA
stormer-0.1.2.dist-info/WHEEL
stormer-0.1.2.dist-info/top_level.txt
stormer-0.1.2.dist-info/RECORD
