Metadata-Version: 2.1
Name: stormer
Version: 0.1.2
Summary: this is a requester for requests.
Home-page: https://github.com/sunglowrise/stormer/
Maintainer: Murray
Maintainer-email: sunglowrise@qq.com
License: MIT
Download-URL: https://github.com/sunglowrise/stormer/
Keywords: stormer,requester,redis,requests
Platform: Platform Independent
Classifier: Programming Language :: Python
Classifier: Intended Audience :: Developers
Classifier: Topic :: Software Development :: Libraries :: Python Modules
Classifier: Topic :: Internet :: WWW/HTTP :: Dynamic Content :: CGI Tools/Libraries
Classifier: Programming Language :: Python :: 3.5
Classifier: Programming Language :: Python :: 3.6
Classifier: Programming Language :: Python :: 3.7
Classifier: Programming Language :: Python :: Implementation :: CPython
Requires-Python: >=3.5
Requires-Dist: requests (>=2.22.0)
Requires-Dist: redis (>=3.3.11)
Requires-Dist: redis-py-cluster (>=2.1.0)
